setup.py
XosUtil.egg-info/PKG-INFO
XosUtil.egg-info/SOURCES.txt
XosUtil.egg-info/dependency_links.txt
XosUtil.egg-info/top_level.txt
xosutil/__init__.py
xosutil/autodiscover_version.py
xosutil/autoversion_setup.py
xosutil/version.py