Metadata-Version: 1.0
Name: XosUtil
Version: 3.1.0
Summary: XOS Utility Library
Home-page: UNKNOWN
Author: Scott Baker
Author-email: scottb@opennetworking.org
License: UNKNOWN
Platform: UNKNOWN
